matchmsextras/__init__.py
matchmsextras/__version__.py
matchmsextras/library_search.py
matchmsextras/networking.py
matchmsextras/plotting_functions.py
matchmsextras/pubchem_lookup.py
matchmsextras-0.4.2.dist-info/LICENSE
matchmsextras-0.4.2.dist-info/METADATA
matchmsextras-0.4.2.dist-info/WHEEL
matchmsextras-0.4.2.dist-info/top_level.txt
matchmsextras-0.4.2.dist-info/RECORD
